meta_dashboard/__init__.py
meta_dashboard/admin.py
meta_dashboard/apps.py
meta_dashboard/navbars.py
meta_dashboard/patterns.py
meta_dashboard/urls.py
meta_dashboard/migrations/__init__.py
meta_dashboard/model_wrappers/__init__.py
meta_dashboard/model_wrappers/ae_initial_model_wrapper.py
meta_dashboard/model_wrappers/death_report_model_wrapper.py
meta_dashboard/model_wrappers/subject_refusal_model_wrapper.py
meta_dashboard/model_wrappers/subject_screening_model_wrapper.py
meta_dashboard/templates/meta_dashboard/bootstrap3/buttons/add_consent_button.html
meta_dashboard/templates/meta_dashboard/bootstrap3/buttons/dashboard_button.html
meta_dashboard/templates/meta_dashboard/bootstrap3/buttons/eligibility_button.html
meta_dashboard/templates/meta_dashboard/bootstrap3/buttons/refusal_button.html
meta_dashboard/templates/meta_dashboard/bootstrap3/buttons/screening_button.html
meta_dashboard/templates/meta_dashboard/bootstrap3/screening/listboard.html
meta_dashboard/templates/meta_dashboard/bootstrap3/subject/dashboard.html
meta_dashboard/templates/meta_dashboard/bootstrap3/subject/listboard.html
meta_dashboard/templates/meta_dashboard/bootstrap3/subject/dashboard/top_bar.html
meta_dashboard/templatetags/__init__.py
meta_dashboard/templatetags/meta_dashboard_extras.py
meta_dashboard/tests/__init__.py
meta_dashboard/tests/admin.py
meta_dashboard/tests/urls.py
meta_dashboard/tests/tests/__init__.py
meta_dashboard/tests/tests/test_model_wrappers.py
meta_dashboard/views/__init__.py
meta_dashboard/views/ae/__init__.py
meta_dashboard/views/ae/ae_listboard_view.py
meta_dashboard/views/ae/death_report_listboard_view.py
meta_dashboard/views/screening/__init__.py
meta_dashboard/views/screening/filters.py
meta_dashboard/views/screening/listboard_view.py
meta_dashboard/views/subject/__init__.py
meta_dashboard/views/subject/dashboard/__init__.py
meta_dashboard/views/subject/dashboard/dashboard_view.py
meta_dashboard/views/subject/listboard/__init__.py
meta_dashboard-0.1.16.dist-info/AUTHORS
meta_dashboard-0.1.16.dist-info/LICENSE
meta_dashboard-0.1.16.dist-info/METADATA
meta_dashboard-0.1.16.dist-info/WHEEL
meta_dashboard-0.1.16.dist-info/top_level.txt
meta_dashboard-0.1.16.dist-info/RECORD
